pyriad/__init__.py
pyriad/agents.py
pyriad/distributions.py
pyriad/memories.py
pyriad/populations.py
pyriad/swarms.py
tests/__init__.py
tests/factories.py
tests/test_agents.py
tests/test_memories.py
tests/test_populations.py
tests/test_swarms.py
pyriad-0.1.2.dist-info/LICENSE
pyriad-0.1.2.dist-info/METADATA
pyriad-0.1.2.dist-info/WHEEL
pyriad-0.1.2.dist-info/top_level.txt
pyriad-0.1.2.dist-info/RECORD
