Metadata-Version: 2.1
Name: pyriad
Version: 0.1.2
Summary: Clustering with nature inspired algorithms
Home-page: https://github.com/Catastropha/pyriad
Author: Teodor Scorpan
Author-email: teodor.scorpan@gmail.com
License: UNKNOWN
Platform: UNKNOWN
Classifier: Programming Language :: Python :: 3.6
Classifier: License :: OSI Approved :: MIT License
Classifier: Operating System :: OS Independent
